{
  "project_info": {
    "project_number": "632069230331",
    "project_id": "contact-demo-23",
    "storage_bucket": "contact-demo-23.appspot.com"
  },
  "client": [
    {
      "client_info": {
        "mobilesdk_app_id": "1:632069230331:android:61c3ce392b1236cfafaa5e",
        "android_client_info": {
          "package_name": "com.startapp.contact_demo"
        }
      },
      "oauth_client": [
        {
          "client_id": "632069230331-iaebpgrett5s82ae6pb0s63lfj8qkiil.apps.googleusercontent.com",
          "client_type": 1,
          "android_info": {
            "package_name": "com.startapp.contact_demo",
            "certificate_hash": "68bf466763ed97f09ee706daa4ac900e8965db21"
          }
        },
        {
          "client_id": "632069230331-ka7s2kt2ogcvnqsv3lvled30l03fdb2d.apps.googleusercontent.com",
          "client_type": 1,
          "android_info": {
            "package_name": "com.startapp.contact_demo",
            "certificate_hash": "b4469d89116312f7a7fef147664130dd74d9b0f1"
          }
        },
        {
          "client_id": "632069230331-52jgukjskv8757a2p6otamnqtumug0lv.apps.googleusercontent.com",
          "client_type": 3
        }
      ],
      "api_key": [
        {
          "current_key": "AIzaSyCSYYApGXalwigXryxP_YcMpENG_5OaBbQ"
        }
      ],
      "services": {
        "appinvite_service": {
          "other_platform_oauth_client": [
            {
              "client_id": "632069230331-52jgukjskv8757a2p6otamnqtumug0lv.apps.googleusercontent.com",
              "client_type": 3
            },
            {
              "client_id": "632069230331-t6upgv2dikig75pg1k71nof7bi6tivlf.apps.googleusercontent.com",
              "client_type": 2,
              "ios_info": {
                "bundle_id": "com.startapp.contactDemo"
              }
            }
          ]
        }
      }
    }
  ],
  "configuration_version": "1"
}